{
  "mode": "genre",
  "genre": "育児",
  "keywords": ["育児", "子育て", "夜泣き", "イヤイヤ期", "寝かしつけ", "離乳食", "保育園", "子ども", "ママ"],
  "executed_at": "2026-05-24 02:14",
  "post_count": 3,
  "posts": [
    {
      "rank": 1,
      "author_name": "mama_no_hack",
      "author_url": "https://www.threads.com/@mama_no_hack",
      "post_text": "「アンパンマンジュースちょうだい！」って言われて、今日もこれでお水飲んでくれてます\n\n水も牛乳も麦茶もいけます。本当アンパンマン様々すぎる😭🙏✨\n（アンパンマン ストローカップ フタ付 Sサイズ 4個入）",
      "likes": 4079,
      "comments": 16,
      "posted_at": "2026-05-20",
      "post_url": "https://www.threads.com/@mama_no_hack/post/DYhZtR8GTR7",
      "matched_keyword": "Phase2:フォロー欄(miketa_ikuji_neko起点)",
      "account_score": 8,
      "post_score": 2
    },
    {
      "rank": 2,
      "author_name": "mamu_food_",
      "author_url": "https://www.threads.com/@mamu_food_",
      "post_text": "【保存版】 保育園栄養士がえらぶ、1歳コンビニ離乳食がこちらですッターこれぜ〜〜〜んぶ無添加だからびっくりだよね！ゴールデンウィークお出かけの時コンビニ使う時ぜひ参考にして〜〜\nでも一つだけ注意してほしいことがあって、\n\n塩分過多になりやすい💦！塩分の１日の目安はこんな感じ！\n・6〜11ヶ月: 1.5g未満\n・1〜2歳: 2.5g〜3.0g未満\n・3〜5歳: 3.5g〜4.5g未満\n・6〜7歳: 4.5g〜5.5g未満\nコンビニの成分表示で『/』以降は添加物だから気をつけて見てみてね〜〜！！\n保育園栄養士の2児ママが毎日離乳食情報や育児の有益情報発信してますっ！！\n離乳食迷子さん１日2分で離乳食の悩みからかいほうされますよっっっ！\n@mamu_food_\nフォロー待ってますっ！",
      "likes": 623,
      "comments": 3,
      "posted_at": "2026-05-04",
      "post_url": "https://www.threads.com/@mamu_food_/post/DX5xb29Eysx",
      "matched_keyword": "Phase2:フォロー欄(miketa_ikuji_neko起点)/離乳食",
      "account_score": 7,
      "post_score": 3
    },
    {
      "rank": 3,
      "author_name": "mamu_food_",
      "author_url": "https://www.threads.com/@mamu_food_",
      "post_text": "【保存版】 保育園栄養士がえらぶ、1歳コンビニ離乳食『ファミマ・LAWSON編』がこちらですッ！これぜ〜〜〜んぶ無添加だからびっくりだよね！ゴールデンウィークお出かけの時コンビニ使う時ぜひ参考にしてね〜〜！\n\nセブン編はこちらですっ！",
      "likes": 159,
      "comments": 1,
      "posted_at": "2026-05-04",
      "post_url": "https://www.threads.com/@mamu_food_/post/DX6g1qTk1CX",
      "matched_keyword": "Phase2:フォロー欄(miketa_ikuji_neko起点)/離乳食",
      "account_score": 7,
      "post_score": 3
    }
  ]
}
