{
  "mode": "genre",
  "genre": "占い",
  "keywords": ["開運", "運気", "スピリチュアル", "金運", "恋愛運", "一粒万倍日", "神社", "引き寄せ"],
  "executed_at": "2026-06-05 03:45",
  "post_count": 10,
  "posts": [
    {
      "rank": 1,
      "author_name": "reikoobaa_uranai",
      "author_url": "https://www.threads.com/@reikoobaa_uranai",
      "post_text": "2本の指でくっつけてみんさい👵\nい い ね す る と 金 運 上 が る け 🍲",
      "likes": 7006,
      "comments": 15,
      "posted_at": "2026-05-06",
      "post_url": "https://www.threads.com/@reikoobaa_uranai/post/DX_qiyyj1g7",
      "matched_keyword": "金運",
      "account_score": 7,
      "post_score": 2
    },
    {
      "rank": 2,
      "author_name": "miraiuranai_rei",
      "author_url": "https://www.threads.com/@miraiuranai_rei",
      "post_text": "やはり、あなたは超強運ですね\nあなたのお財布、\n福でパンッパンになる",
      "likes": 2968,
      "comments": 6,
      "posted_at": "2026-04-15",
      "post_url": "https://www.threads.com/@miraiuranai_rei/post/DXJSb8yFilR",
      "matched_keyword": "金運",
      "account_score": 7,
      "post_score": 2
    },
    {
      "rank": 3,
      "author_name": "nkohei.1111",
      "author_url": "https://www.threads.com/@nkohei.1111",
      "post_text": "大強運。大吉。大開運。\n大強運。大吉。大開運。\n大強運。大吉。大開運。\nここから急激に\n運気爆上がりしていく🍀",
      "likes": 1970,
      "comments": 11,
      "posted_at": "2026-05-14",
      "post_url": "https://www.threads.com/@nkohei.1111/post/DYUNfscCegJ",
      "matched_keyword": "開運",
      "account_score": 7,
      "post_score": 2
    },
    {
      "rank": 4,
      "author_name": "yuki_suhikoti",
      "author_url": "https://www.threads.com/@yuki_suhikoti",
      "post_text": "今日は…最強の吉日である天赦日と金運の寅の日が重なる最強開運日\n実は…\n\n天赦日は年に 5〜6回しかないレア日\nしかも虎の日と重なる最強開運日💫\n天赦日＝すべてを許す日\n寅の日＝金運を高める日\n【日常でできる開運アクション】\n✔ 財布の中を整える（レシート・不要なカードを手放す）\n✔ お金を払うとき丁寧に扱う\n✔ 小さくても“やりたかったこと”を始める\n✔ 「ありがとう」をちゃんと伝える\n✔ 使ったお金にポジティブな意味づけをする\n【気をつけること】\n⚠ 衝動買い\n⚠ お金を雑に扱う\n⚠ 「どうせ無理」と決めつける\n⚠ ローン契約やお金の貸し借り\n今日は大きく変えるより\n「整えること」が開運につながる🌿\nまずは水回りと床はキレイにしておこう!\n今日も素敵な1日を～🖐",
      "likes": 1529,
      "comments": 1,
      "posted_at": "2026-05-03",
      "post_url": "https://www.threads.com/@yuki_suhikoti/post/DX5RUNIAYN6",
      "matched_keyword": "開運",
      "account_score": 8,
      "post_score": 3
    },
    {
      "rank": 5,
      "author_name": "ruri_reishi888",
      "author_url": "https://www.threads.com/@ruri_reishi888",
      "post_text": "すみません、私、嘘はつきません。\n明日は一粒万倍日×天恩日×神吉日×月徳日。\nその前日にこの投稿が見れた貴方様、\n運命の流れが静かに変わってます。\n4月7日、4月8日にいいねできた人から\n流れ、変わります。",
      "likes": 1372,
      "comments": 7,
      "posted_at": "2026-04-07",
      "post_url": "https://www.threads.com/@ruri_reishi888/post/DW1Ch3UiTB5",
      "matched_keyword": "一粒万倍日",
      "account_score": 7,
      "post_score": 3
    },
    {
      "rank": 6,
      "author_name": "okkko.3535",
      "author_url": "https://www.threads.com/@okkko.3535",
      "post_text": "オカマだからハッキリ言うわよ。\n男からグイグイきた恋愛で、\n最終的に女のほうが執着してる。\nあれ、その男のことが好きなんじゃないの。\n「自分を好きになって、動いてくれた」\nその事実に、依存してるだけよ。\n選ばれた事実に、\n溺れてるだけ。\n\n相手が好きなのか。\n相手に好かれた自分が好きなのか。\nそこを混同したまま執着すると、一生答えの出ない迷路を歩き続けることになるわ。\n怖いのはね、その迷路の中にいる間は、\n誰も自分が迷子だと気づかないこと。\n好きだと思ってた感情が、実は「あの頃の自分」への未練だったりするのよ。",
      "likes": 1303,
      "comments": 16,
      "posted_at": "2026-05-05",
      "post_url": "https://www.threads.com/@okkko.3535/post/DX9FvgaCcuB",
      "matched_keyword": "恋愛運",
      "account_score": 7,
      "post_score": 3
    },
    {
      "rank": 7,
      "author_name": "koyasan369",
      "author_url": "https://www.threads.com/@koyasan369",
      "post_text": "まさかまだ、起きてる人いますか？\nもし、奇跡的に起きてる人がいたら超ラッキーです。\n2026/5/2（土）一年に一度の丙午×蠍座満月×一粒万倍日の重なる特別な日です。\n精霊が集結する時間の\n1:20-3:20の短い間だけ。\n「🙏」を置いてくれた方へ\n沖縄から私が視えたまま、正直にお伝えします\n\nたくさんのご依頼ありがとうございます🌊\nご希望の方は、コヤをフォロー後、プロフィールのリンクよりお越しください🤲",
      "likes": 1019,
      "comments": 758,
      "posted_at": "2026-05-01",
      "post_url": "https://www.threads.com/@koyasan369/post/DXzXHdnErlj",
      "matched_keyword": "一粒万倍日",
      "account_score": 9,
      "post_score": 3
    },
    {
      "rank": 8,
      "author_name": "shiera_uranai_dynamite",
      "author_url": "https://www.threads.com/@shiera_uranai_dynamite",
      "post_text": "この日だけはスルーするんじゃない\n5月4日（月）\n最強開運日‼️\n最強開運日‼️\nもう一度言うわよ\n最強開運日よ‼️‼️‼️\n「🙏」を置いた方全員\nずっと引きずった疫病神にバイバイ\n最高の2026年がここから始まるわ",
      "likes": 817,
      "comments": 318,
      "posted_at": "2026-05-04",
      "post_url": "https://www.threads.com/@shiera_uranai_dynamite/post/DX56Cl_AcDt",
      "matched_keyword": "開運",
      "account_score": 8,
      "post_score": 3
    },
    {
      "rank": 9,
      "author_name": "minaguchimoko",
      "author_url": "https://www.threads.com/@minaguchimoko",
      "post_text": "明日から10年間運気最強だぞー‼️\nおらーーー✨✨✨",
      "likes": 671,
      "comments": 9,
      "posted_at": "2026-06-04",
      "post_url": "https://www.threads.com/@minaguchimoko/post/DZJ3FavkVh8",
      "matched_keyword": "運気",
      "account_score": 7,
      "post_score": 2
    },
    {
      "rank": 10,
      "author_name": "soramame.uranai",
      "author_url": "https://www.threads.com/@soramame.uranai",
      "post_text": "5月22日、\n超開運が始まるよ。\n「超」が5個じゃ\n足りないくらいのやつが来るから。🌈",
      "likes": 626,
      "comments": 0,
      "posted_at": "2026-05-21",
      "post_url": "https://www.threads.com/@soramame.uranai/post/DYmm_PIiJMP",
      "matched_keyword": "開運",
      "account_score": 7,
      "post_score": 2
    }
  ]
}
